sphinxcontrib_dashdomain-0.1.1-py2.7-nspkg.pth
sphinxcontrib/dash/__init__.py
sphinxcontrib/dash/builder.py
sphinxcontrib/dash/domain.py
sphinxcontrib/dash/icon.png
sphinxcontrib_dashdomain-0.1.1.dist-info/DESCRIPTION.rst
sphinxcontrib_dashdomain-0.1.1.dist-info/METADATA
sphinxcontrib_dashdomain-0.1.1.dist-info/RECORD
sphinxcontrib_dashdomain-0.1.1.dist-info/WHEEL
sphinxcontrib_dashdomain-0.1.1.dist-info/metadata.json
sphinxcontrib_dashdomain-0.1.1.dist-info/namespace_packages.txt
sphinxcontrib_dashdomain-0.1.1.dist-info/top_level.txt
