Metadata-Version: 2.0
Name: sphinxcontrib-dashdomain
Version: 0.1.1
Summary: Sphinx "dash domain" and "builder" extension
Home-page: http://bitbucket.org/togakushi/sphinxcontrib-dashdomain
Author: @togakushi
Author-email: nina.togakushi at gmail dot com
License: BSD
Download-URL: http://pypi.python.org/pypi/sphinxcontrib-dashdomain
Platform: any
Classifier: Environment :: Console
Classifier: Environment :: Web Environment
Classifier: Framework :: Sphinx :: Extension
Classifier: Intended Audience :: Developers
Classifier: License :: OSI Approved :: BSD License
Classifier: Operating System :: OS Independent
Classifier: Programming Language :: Python
Classifier: Topic :: Documentation
Classifier: Topic :: Utilities
Requires-Dist: Sphinx (>=1.0)
